tests/__init__.py
tests/test_cache.py
tests/test_decorator.py
tests/test_encoder.py
tests/test_formatter.py
tests/test_logger.py
tests/test_printable.py
vulcan_utils/__init__.py
vulcan_utils/cache.py
vulcan_utils/decorator.py
vulcan_utils/encoder.py
vulcan_utils/formatter.py
vulcan_utils/logger.py
vulcan_utils/printable.py
vulcan_utils-1.12.4.dist-info/LICENSE
vulcan_utils-1.12.4.dist-info/METADATA
vulcan_utils-1.12.4.dist-info/WHEEL
vulcan_utils-1.12.4.dist-info/top_level.txt
vulcan_utils-1.12.4.dist-info/RECORD
