Metadata-Version: 2.1
Name: vulcan-utils
Version: 1.12.4
Summary: A utility package for Python
License-File: LICENSE
Requires-Dist: coloredlogs
